{
  "round": 3,
  "strategy": "SFJ_15Dworkshop_lesson5_countertrend_LS_crypto",
  "symbol": "BNBUSDT HOT",
  "timeframe": "Daily",
  "is_range": [
    "2022/01/01",
    "2026/01/01"
  ],
  "target_np": 100000.0,
  "target_met": false,
  "notes": {
    "logic": "BUY when C crosses over lower BB; SHORT when C crosses under upper BB",
    "exits": "Reversal only -- no STP or LMT",
    "contract": "_Crypto1MUSD=Round(1000000/C,0)",
    "is_window": "2022/01/01-2026/01/01 (chart trimmed via set_instrument_data_range)",
    "r1r2_ceiling": "LL=24 SL=1.75 LS=23 SS=3 NP=35182 MDD=-5200 Obj=238043 16tr (R1=R2 5-conv)",
    "r3_goal": "Raise target to 100K; hunt ultra-high-freq / low-SS / LL+LS boundary pushes for a higher-NP regime, else confirm 100K unreachable"
  },
  "best_params": {
    "attempt": 10,
    "name": "10_adaptive_zoom2",
    "LENGTH_LONG": 15.0,
    "STDDEV_LONG": 2.175,
    "LENGTH_SHORT": 21.0,
    "STDDEV_SHORT": 3.15,
    "objective": 272358.2770707203,
    "net_profit": 42541.7,
    "max_drawdown": -6644.91,
    "total_trades": 14,
    "target_met": false,
    "combos": 4459,
    "rows": 3822,
    "timestamp": "2026-06-15T20:41:52.445800"
  },
  "all_attempts": [
    {
      "attempt": 1,
      "name": "01_ultra_high_freq",
      "LENGTH_LONG": 4.0,
      "STDDEV_LONG": 1.5,
      "LENGTH_SHORT": 9.0,
      "STDDEV_SHORT": 1.2,
      "objective": 117353.32318916102,
      "net_profit": 23489.2,
      "max_drawdown": -4701.55,
      "total_trades": 109,
      "target_met": false,
      "combos": 4851,
      "rows": 3953,
      "timestamp": "2026-06-15T20:35:21.158136"
    },
    {
      "attempt": 2,
      "name": "02_short_LL_midLS",
      "LENGTH_LONG": 10.0,
      "STDDEV_LONG": 2.25,
      "LENGTH_SHORT": 18.0,
      "STDDEV_SHORT": 3.0,
      "objective": 213603.41752709966,
      "net_profit": 37674.6,
      "max_drawdown": -6644.91,
      "total_trades": 14,
      "target_met": false,
      "combos": 4235,
      "rows": 2451,
      "timestamp": "2026-06-15T20:36:04.330550"
    },
    {
      "attempt": 3,
      "name": "03_mid_LL_lowSS",
      "LENGTH_LONG": 25.0,
      "STDDEV_LONG": 2.0,
      "LENGTH_SHORT": 31.0,
      "STDDEV_SHORT": 0.8,
      "objective": 16764.49304266194,
      "net_profit": 13887.6,
      "max_drawdown": -11504.4,
      "total_trades": 31,
      "target_met": false,
      "combos": 3696,
      "rows": 3696,
      "timestamp": "2026-06-15T20:36:48.496550"
    },
    {
      "attempt": 4,
      "name": "04_champ_reconfirm",
      "LENGTH_LONG": 25.0,
      "STDDEV_LONG": 1.7,
      "LENGTH_SHORT": 19.0,
      "STDDEV_SHORT": 3.1,
      "objective": 187098.90410544325,
      "net_profit": 35772.9,
      "max_drawdown": -6839.7,
      "total_trades": 14,
      "target_met": false,
      "combos": 3402,
      "rows": 2869,
      "timestamp": "2026-06-15T20:37:31.782984"
    },
    {
      "attempt": 5,
      "name": "05_LL_push",
      "LENGTH_LONG": 40.0,
      "STDDEV_LONG": 1.0,
      "LENGTH_SHORT": 20.0,
      "STDDEV_SHORT": 3.0,
      "objective": 55191.51784798272,
      "net_profit": 21658.8,
      "max_drawdown": -8499.56,
      "total_trades": 14,
      "target_met": false,
      "combos": 2550,
      "rows": 459,
      "timestamp": "2026-06-15T20:38:13.767705"
    },
    {
      "attempt": 6,
      "name": "06_LS_push",
      "LENGTH_LONG": 15.0,
      "STDDEV_LONG": 1.5,
      "LENGTH_SHORT": 85.0,
      "STDDEV_SHORT": 3.5,
      "objective": 147402.47427505365,
      "net_profit": 26990.3,
      "max_drawdown": -4942.09,
      "total_trades": 15,
      "target_met": false,
      "combos": 3740,
      "rows": 1680,
      "timestamp": "2026-06-15T20:38:58.568582"
    },
    {
      "attempt": 7,
      "name": "07_tight_SS_hifreq",
      "LENGTH_LONG": 5.0,
      "STDDEV_LONG": 1.4,
      "LENGTH_SHORT": 17.0,
      "STDDEV_SHORT": 0.6,
      "objective": 82007.69115506273,
      "net_profit": 19942.9,
      "max_drawdown": -4849.78,
      "total_trades": 105,
      "target_met": false,
      "combos": 3630,
      "rows": 3575,
      "timestamp": "2026-06-15T20:39:42.279856"
    },
    {
      "attempt": 8,
      "name": "08_asym_shortLL_longLS",
      "LENGTH_LONG": 12.0,
      "STDDEV_LONG": 1.5,
      "LENGTH_SHORT": 80.0,
      "STDDEV_SHORT": 3.5,
      "objective": 142818.4086671833,
      "net_profit": 26567.3,
      "max_drawdown": -4942.09,
      "total_trades": 15,
      "target_met": false,
      "combos": 2100,
      "rows": 953,
      "timestamp": "2026-06-15T20:40:24.338426"
    },
    {
      "attempt": 9,
      "name": "09_adaptive_zoom1",
      "LENGTH_LONG": 14.0,
      "STDDEV_LONG": 2.15,
      "LENGTH_SHORT": 18.0,
      "STDDEV_SHORT": 3.0,
      "objective": 229483.12166906704,
      "net_profit": 39049.9,
      "max_drawdown": -6644.91,
      "total_trades": 14,
      "target_met": false,
      "combos": 3645,
      "rows": 2309,
      "timestamp": "2026-06-15T20:41:09.041492"
    },
    {
      "attempt": 10,
      "name": "10_adaptive_zoom2",
      "LENGTH_LONG": 15.0,
      "STDDEV_LONG": 2.175,
      "LENGTH_SHORT": 21.0,
      "STDDEV_SHORT": 3.15,
      "objective": 272358.2770707203,
      "net_profit": 42541.7,
      "max_drawdown": -6644.91,
      "total_trades": 14,
      "target_met": false,
      "combos": 4459,
      "rows": 3822,
      "timestamp": "2026-06-15T20:41:52.445800"
    },
    {
      "attempt": 11,
      "name": "11_adaptive_zoom3",
      "LENGTH_LONG": 15.0,
      "STDDEV_LONG": 2.175,
      "LENGTH_SHORT": 20.0,
      "STDDEV_SHORT": 3.125,
      "objective": 272358.2770707203,
      "net_profit": 42541.7,
      "max_drawdown": -6644.91,
      "total_trades": 14,
      "target_met": false,
      "combos": 2025,
      "rows": 1800,
      "timestamp": "2026-06-15T20:42:34.724658"
    }
  ]
}