{
  "stage1": {
    "symbol": "ETHUSDT HOT",
    "champion_obj": {
      "PivMult": 0.175,
      "ATRMult": 15.75,
      "ReentryBars": 29.0,
      "net_profit": 3619.98,
      "max_drawdown": -460.406,
      "objective": 28462.390152170043,
      "total_trades": 68
    },
    "champion_np": {
      "PivMult": 0.2,
      "ATRMult": 15.5,
      "ReentryBars": 28.0,
      "net_profit": 3669.87,
      "max_drawdown": -484.625,
      "objective": 27790.447906938356,
      "total_trades": 69
    },
    "candidates": [
      {
        "PivMult": 0.175,
        "ATRMult": 15.75,
        "ReentryBars": 29.0,
        "net_profit": 3619.98,
        "max_drawdown": -460.406,
        "objective": 28462.390152170043,
        "total_trades": 68
      },
      {
        "PivMult": 0.2,
        "ATRMult": 15.5,
        "ReentryBars": 28.0,
        "net_profit": 3669.87,
        "max_drawdown": -484.625,
        "objective": 27790.447906938356,
        "total_trades": 69
      },
      {
        "PivMult": 0.2,
        "ATRMult": 16.0,
        "ReentryBars": 30.0,
        "net_profit": 3495.0,
        "max_drawdown": -460.643,
        "objective": 26517.33555052394,
        "total_trades": 66
      },
      {
        "PivMult": 0.2,
        "ATRMult": 15.25,
        "ReentryBars": 28.0,
        "net_profit": 3528.83,
        "max_drawdown": -523.069,
        "objective": 23806.880485939717,
        "total_trades": 72
      }
    ],
    "convergence": [
      {
        "round": 2,
        "prev_obj": 28462.390152170043,
        "obj": 28462.390152170043,
        "gain_pct": 0.0
      }
    ],
    "timestamp": "2026-07-01T23:46:46.661542"
  },
  "stage2": {
    "results": {
      "is": {
        "0": {
          "net_profit": 3619.98,
          "max_drawdown": -460.406,
          "total_trades": 68
        },
        "1": {
          "net_profit": 3669.87,
          "max_drawdown": -484.625,
          "total_trades": 69
        },
        "2": {
          "net_profit": 3495.0,
          "max_drawdown": -460.643,
          "total_trades": 66
        },
        "3": {
          "net_profit": 3528.83,
          "max_drawdown": -523.069,
          "total_trades": 72
        }
      },
      "full": {
        "0": {
          "net_profit": 3375.67,
          "max_drawdown": -1286.64,
          "total_trades": 94
        },
        "1": {
          "net_profit": 3375.49,
          "max_drawdown": -1251.78,
          "total_trades": 98
        },
        "2": {
          "net_profit": 3477.72,
          "max_drawdown": -1228.3,
          "total_trades": 90
        },
        "3": {
          "net_profit": 3173.1,
          "max_drawdown": -1238.1,
          "total_trades": 101
        }
      }
    },
    "report": [
      {
        "idx": 0,
        "params": {
          "PivMult": 0.175,
          "ATRMult": 15.75,
          "ReentryBars": 29.0
        },
        "np_is": 3619.98,
        "mdd_is": -460.406,
        "np_full": 3375.67,
        "mdd_full": -1286.64,
        "oos_np": -244.31,
        "mdd_break": true,
        "pass": false,
        "break_ratio": 2.795
      },
      {
        "idx": 1,
        "params": {
          "PivMult": 0.2,
          "ATRMult": 15.5,
          "ReentryBars": 28.0
        },
        "np_is": 3669.87,
        "mdd_is": -484.625,
        "np_full": 3375.49,
        "mdd_full": -1251.78,
        "oos_np": -294.38,
        "mdd_break": true,
        "pass": false,
        "break_ratio": 2.583
      },
      {
        "idx": 2,
        "params": {
          "PivMult": 0.2,
          "ATRMult": 16.0,
          "ReentryBars": 30.0
        },
        "np_is": 3495.0,
        "mdd_is": -460.643,
        "np_full": 3477.72,
        "mdd_full": -1228.3,
        "oos_np": -17.28,
        "mdd_break": true,
        "pass": false,
        "break_ratio": 2.666
      },
      {
        "idx": 3,
        "params": {
          "PivMult": 0.2,
          "ATRMult": 15.25,
          "ReentryBars": 28.0
        },
        "np_is": 3528.83,
        "mdd_is": -523.069,
        "np_full": 3173.1,
        "mdd_full": -1238.1,
        "oos_np": -355.73,
        "mdd_break": true,
        "pass": false,
        "break_ratio": 2.367
      }
    ],
    "winner": {
      "idx": 2,
      "params": {
        "PivMult": 0.2,
        "ATRMult": 16.0,
        "ReentryBars": 30.0
      },
      "np_is": 3495.0,
      "mdd_is": -460.643,
      "np_full": 3477.72,
      "mdd_full": -1228.3,
      "oos_np": -17.28,
      "mdd_break": true,
      "pass": false,
      "break_ratio": 2.666
    },
    "main_champ": {
      "PivMult": 0.2,
      "ATRMult": 16.0,
      "ReentryBars": 30.0
    },
    "timestamp": "2026-07-01T23:46:46.758959"
  },
  "stage3": {
    "baseline": {
      "net_profit": 3495.0,
      "max_drawdown": -460.643
    },
    "modules": {
      "M1": {
        "signal": "SFJ_15Dworkshop_lesson4_ATRstop",
        "params": {
          "STP": 22.0
        },
        "net_profit": 3546.51,
        "max_drawdown": -460.643,
        "total_trades": 66,
        "delta_np_pct": 1.47
      },
      "M2": {
        "signal": "SFJ_15Dworkshop_lesson9_1_TrailingStop",
        "params": {
          "ATRSTP": 35.2
        },
        "net_profit": 3498.15,
        "max_drawdown": -542.608,
        "total_trades": 75,
        "delta_np_pct": 0.09
      },
      "M3": {
        "signal": "SFJ_15Dworkshop_lesson10_3_EntryBarsAfterExit",
        "params": {
          "EXITBAR": 156.0
        },
        "net_profit": 3793.85,
        "max_drawdown": -450.977,
        "total_trades": 80,
        "delta_np_pct": 8.55
      },
      "M4": {
        "signal": "SFJ_15Dworkshop_lesson11_3_high_volatility_exit",
        "params": {
          "DAYRANGE": 5.58
        },
        "net_profit": 3627.31,
        "max_drawdown": -460.643,
        "total_trades": 70,
        "delta_np_pct": 3.79
      },
      "M5": {
        "signal": "QuantPass_PT_Exit",
        "params": {
          "PT_Base": 0.585
        },
        "net_profit": 4252.36,
        "max_drawdown": -460.643,
        "total_trades": 67,
        "delta_np_pct": 21.67
      },
      "M6": {
        "signal": "RescueTeamExit",
        "params": {
          "Length": 40.0,
          "std": 4.1
        },
        "net_profit": 4475.92,
        "max_drawdown": -496.278,
        "total_trades": 84,
        "delta_np_pct": 28.07
      }
    },
    "timestamp": "2026-07-05T21:29:15.248840"
  },
  "stage4": {
    "baseline": {
      "net_profit": 3477.72,
      "max_intraday_drawdown": -1228.3
    },
    "steps": [
      {
        "step": 1,
        "candidate": "M6",
        "signal": "RescueTeamExit",
        "enabled": [
          "RescueTeamExit"
        ],
        "net_profit": 4221.48,
        "max_intraday_drawdown": -1228.3,
        "romad": 3.4368,
        "prev_romad": 2.8313,
        "delta_romad_pct": 21.39,
        "decision": "KEEP",
        "valid": true
      },
      {
        "step": 2,
        "candidate": "M5",
        "signal": "QuantPass_PT_Exit",
        "enabled": [
          "RescueTeamExit",
          "QuantPass_PT_Exit"
        ],
        "net_profit": 5921.09,
        "max_intraday_drawdown": -656.978,
        "romad": 9.0126,
        "prev_romad": 3.4368,
        "delta_romad_pct": 162.23,
        "decision": "KEEP",
        "valid": true
      },
      {
        "step": 3,
        "candidate": "M3",
        "signal": "SFJ_15Dworkshop_lesson10_3_EntryBarsAfterExit",
        "enabled": [
          "RescueTeamExit",
          "QuantPass_PT_Exit",
          "SFJ_15Dworkshop_lesson10_3_EntryBarsAfterExit"
        ],
        "net_profit": 4372.56,
        "max_intraday_drawdown": -1178.57,
        "romad": 3.7101,
        "prev_romad": 9.0126,
        "delta_romad_pct": -58.83,
        "decision": "discard",
        "valid": true
      },
      {
        "step": 4,
        "candidate": "M4",
        "signal": "SFJ_15Dworkshop_lesson11_3_high_volatility_exit",
        "enabled": [
          "RescueTeamExit",
          "QuantPass_PT_Exit",
          "SFJ_15Dworkshop_lesson11_3_high_volatility_exit"
        ],
        "net_profit": 6006.17,
        "max_intraday_drawdown": -656.978,
        "romad": 9.1421,
        "prev_romad": 9.0126,
        "delta_romad_pct": 1.44,
        "decision": "KEEP",
        "valid": true
      },
      {
        "step": 5,
        "candidate": "M1",
        "signal": "SFJ_15Dworkshop_lesson4_ATRstop",
        "enabled": [
          "RescueTeamExit",
          "QuantPass_PT_Exit",
          "SFJ_15Dworkshop_lesson11_3_high_volatility_exit",
          "SFJ_15Dworkshop_lesson4_ATRstop"
        ],
        "net_profit": 5995.79,
        "max_intraday_drawdown": -656.978,
        "romad": 9.1263,
        "prev_romad": 9.1421,
        "delta_romad_pct": -0.17,
        "decision": "discard",
        "valid": true
      },
      {
        "step": 6,
        "candidate": "M2",
        "signal": "SFJ_15Dworkshop_lesson9_1_TrailingStop",
        "enabled": [
          "RescueTeamExit",
          "QuantPass_PT_Exit",
          "SFJ_15Dworkshop_lesson11_3_high_volatility_exit",
          "SFJ_15Dworkshop_lesson9_1_TrailingStop"
        ],
        "net_profit": 5905.93,
        "max_intraday_drawdown": -800.582,
        "romad": 7.377,
        "prev_romad": 9.1421,
        "delta_romad_pct": -19.31,
        "decision": "discard",
        "valid": true
      }
    ],
    "final_kept": [
      "M6",
      "M5",
      "M4"
    ],
    "final_romad": 9.1421,
    "timestamp": "2026-07-05T21:46:43.181178"
  }
}