{
  "round": 2,
  "strategy": "_2021Basic_Osc_NQ",
  "symbol": "CME.NQ HOT",
  "timeframe": "60min",
  "target_np": 800000.0,
  "target_met": false,
  "notes": {
    "logic": "BUY when C crosses over BollingerBand(C,LEN,LE); SHORT when C crosses under BollingerBand(C,LEN,SE)",
    "exits": "STP×ATR(10) stop + LMT×ATR(10) limit",
    "r1_champion": "LEN=3 LE=-1.25 SE=1.5 STP=1.0 LMT=18.5 NP=453,610 MDD=-62,280 obj=3,303,822 trades=1427",
    "r2_focus": "LMT extension (18.5→30+), LEN=1-2 probe, fine LE/SE/STP tuning",
    "key_r1": "LMT still rising at R1's max; LEN=3 dominant; LE=-1.25 SE=1.5 consistent"
  },
  "best_params": {
    "attempt": 10,
    "name": "10_adaptive_zoom1",
    "LEN": 3.0,
    "LE": -1.25,
    "SE": 1.5,
    "STP": 1.0,
    "LMT": 18.5,
    "objective": 3303821.966923571,
    "net_profit": 453610.0,
    "max_drawdown": -62280.0,
    "total_trades": 1427,
    "target_met": false,
    "combos": 4875,
    "rows": 2808,
    "timestamp": "2026-05-23T15:49:21.399044"
  },
  "all_attempts": [
    {
      "attempt": 1,
      "name": "01_lmt_extend",
      "LEN": 3.0,
      "LE": -1.25,
      "SE": 1.5,
      "STP": 0.75,
      "LMT": 22.0,
      "objective": 2273444.7169976127,
      "net_profit": 441825.0,
      "max_drawdown": -85865.0,
      "total_trades": 1493,
      "target_met": false,
      "combos": 4032,
      "rows": 3492,
      "timestamp": "2026-05-23T15:37:42.325117"
    },
    {
      "attempt": 2,
      "name": "02_len_short",
      "LEN": 4.0,
      "LE": -1.5,
      "SE": 2.0,
      "STP": 0.75,
      "LMT": 23.0,
      "objective": 3651802.5825186335,
      "net_profit": 434320.0,
      "max_drawdown": -51655.0,
      "total_trades": 1158,
      "target_met": false,
      "combos": 1512,
      "rows": 1152,
      "timestamp": "2026-05-23T15:38:51.026885"
    },
    {
      "attempt": 3,
      "name": "03_le_fine",
      "LEN": 3.0,
      "LE": -1.25,
      "SE": 1.5,
      "STP": 0.75,
      "LMT": 20.0,
      "objective": 2455858.211825488,
      "net_profit": 438765.0,
      "max_drawdown": -78390.0,
      "total_trades": 1555,
      "target_met": false,
      "combos": 1584,
      "rows": 1128,
      "timestamp": "2026-05-23T15:39:59.037515"
    },
    {
      "attempt": 4,
      "name": "04_se_fine",
      "LEN": 3.0,
      "LE": -1.25,
      "SE": 1.5,
      "STP": 0.75,
      "LMT": 20.0,
      "objective": 2455858.211825488,
      "net_profit": 438765.0,
      "max_drawdown": -78390.0,
      "total_trades": 1555,
      "target_met": false,
      "combos": 3600,
      "rows": 3294,
      "timestamp": "2026-05-23T15:41:17.054131"
    },
    {
      "attempt": 5,
      "name": "05_stp_fine",
      "LEN": 3.0,
      "LE": -1.25,
      "SE": 1.5,
      "STP": 0.75,
      "LMT": 20.0,
      "objective": 2455858.211825488,
      "net_profit": 438765.0,
      "max_drawdown": -78390.0,
      "total_trades": 1555,
      "target_met": false,
      "combos": 4800,
      "rows": 4350,
      "timestamp": "2026-05-23T15:42:49.346092"
    },
    {
      "attempt": 6,
      "name": "06_lmt_fine_high",
      "LEN": 4.0,
      "LE": -1.5,
      "SE": 1.75,
      "STP": 0.75,
      "LMT": 22.5,
      "objective": 3655082.474591037,
      "net_profit": 434515.0,
      "max_drawdown": -51655.0,
      "total_trades": 1160,
      "target_met": false,
      "combos": 3330,
      "rows": 3404,
      "timestamp": "2026-05-23T15:44:18.203747"
    },
    {
      "attempt": 7,
      "name": "07_len3_wide_se",
      "LEN": 3.0,
      "LE": -1.0,
      "SE": 1.5,
      "STP": 1.0,
      "LMT": 15.0,
      "objective": 2154429.0187891442,
      "net_profit": 380100.0,
      "max_drawdown": -67060.0,
      "total_trades": 1747,
      "target_met": false,
      "combos": 1890,
      "rows": 1125,
      "timestamp": "2026-05-23T15:45:20.623187"
    },
    {
      "attempt": 8,
      "name": "08_high_len_lmt",
      "LEN": 30.0,
      "LE": -1.0,
      "SE": 2.0,
      "STP": 1.25,
      "LMT": 30.0,
      "objective": 1183224.271267723,
      "net_profit": 336890.0,
      "max_drawdown": -95920.0,
      "total_trades": 1526,
      "target_met": false,
      "combos": 2160,
      "rows": 2160,
      "timestamp": "2026-05-23T15:46:31.944544"
    },
    {
      "attempt": 9,
      "name": "09_global_r2",
      "LEN": 17.0,
      "LE": -2.0,
      "SE": 4.0,
      "STP": 1.5,
      "LMT": 30.0,
      "objective": 2257770.299245659,
      "net_profit": 398285.0,
      "max_drawdown": -70260.0,
      "total_trades": 566,
      "target_met": false,
      "combos": 3600,
      "rows": 3320,
      "timestamp": "2026-05-23T15:47:53.466891"
    },
    {
      "attempt": 10,
      "name": "10_adaptive_zoom1",
      "LEN": 3.0,
      "LE": -1.25,
      "SE": 1.5,
      "STP": 1.0,
      "LMT": 18.5,
      "objective": 3303821.966923571,
      "net_profit": 453610.0,
      "max_drawdown": -62280.0,
      "total_trades": 1427,
      "target_met": false,
      "combos": 4875,
      "rows": 2808,
      "timestamp": "2026-05-23T15:49:21.399044"
    },
    {
      "attempt": 11,
      "name": "11_adaptive_zoom2",
      "LEN": 3.0,
      "LE": -1.25,
      "SE": 1.5,
      "STP": 1.0,
      "LMT": 18.5,
      "objective": 3303821.966923571,
      "net_profit": 453610.0,
      "max_drawdown": -62280.0,
      "total_trades": 1427,
      "target_met": false,
      "combos": 4875,
      "rows": 2808,
      "timestamp": "2026-05-23T15:50:50.608021"
    },
    {
      "attempt": 12,
      "name": "12_adaptive_zoom3",
      "LEN": 3.0,
      "LE": -1.25,
      "SE": 1.5,
      "STP": 1.0,
      "LMT": 18.5,
      "objective": 3303821.966923571,
      "net_profit": 453610.0,
      "max_drawdown": -62280.0,
      "total_trades": 1427,
      "target_met": false,
      "combos": 4125,
      "rows": 2376,
      "timestamp": "2026-05-23T15:52:15.804998"
    }
  ]
}